py2graphql/__init__.py
py2graphql/core.py
py2graphql/exception.py
py2graphql/middleware.py
py2graphql/py.typed
py2graphql/serialization.py
py2graphql/tests.py
py2graphql/types.py
py2graphql-0.23.0.dist-info/LICENSE
py2graphql-0.23.0.dist-info/METADATA
py2graphql-0.23.0.dist-info/WHEEL
py2graphql-0.23.0.dist-info/RECORD
