Metadata-Version: 2.1
Name: py2graphql
Version: 0.23.0
Summary: Pythonic GraphQL Client
Home-page: https://github.com/willemt/py2graphql
License: MIT
Keywords: graphql
Author: Willem Thiart
Author-email: himself@willemthiart.com
Requires-Python: >=3.9,<4.0
Classifier: License :: OSI Approved :: MIT License
Classifier: Programming Language :: Python :: 3
Classifier: Programming Language :: Python :: 3.9
Classifier: Programming Language :: Python :: 3.10
Classifier: Programming Language :: Python :: 3.11
Classifier: Programming Language :: Python :: 3.12
Classifier: Topic :: Software Development :: Libraries :: Python Modules
Provides-Extra: aiohttp
Provides-Extra: all
Provides-Extra: httpx
Requires-Dist: addict (>=2.2.1,<3.0.0)
Requires-Dist: aiohttp (>=3.6.2,<4.0.0) ; extra == "aiohttp" or extra == "all"
Requires-Dist: httpx (>=0.23.0,<0.24.0) ; extra == "httpx" or extra == "all"
Requires-Dist: requests (>=2.24.0,<3.0.0)
Requires-Dist: tenacity (>=6.2.0,<10.0.0)
Project-URL: Repository, https://github.com/willemt/py2graphql
